summers/__init__.py
summers/cc.py
summers/di.py
summers/sc_imp.py
summers/sc_txt.py
summers-0.2.3.dist-info/METADATA
summers-0.2.3.dist-info/WHEEL
summers-0.2.3.dist-info/top_level.txt
summers-0.2.3.dist-info/RECORD
