Metadata-Version: 2.1
Name: summers
Version: 0.2.3
Summary: 一个 python 依赖注入框架 <A dependency injection toolkit like Spring (java framework)>
Home-page: https://github.com/tuijs/summers
Author: weiyi
Author-email: 272654394@qq.com
License: UNKNOWN
Platform: UNKNOWN
